YcChuangyeKe2019ZhongwenBiji/README.md
YcChuangyeKe2019ZhongwenBiji/__init__.py
YcChuangyeKe2019ZhongwenBiji/__main__.py
YcChuangyeKe2019ZhongwenBiji/file.epub
YcChuangyeKe2019ZhongwenBiji/index.html
YcChuangyeKe2019ZhongwenBiji/css/__init__.py
YcChuangyeKe2019ZhongwenBiji/css/annotations.css
YcChuangyeKe2019ZhongwenBiji/css/main.css
YcChuangyeKe2019ZhongwenBiji/css/normalize.css
YcChuangyeKe2019ZhongwenBiji/css/popup.css
YcChuangyeKe2019ZhongwenBiji/font/__init__.py
YcChuangyeKe2019ZhongwenBiji/font/fontello.eot
YcChuangyeKe2019ZhongwenBiji/font/fontello.svg
YcChuangyeKe2019ZhongwenBiji/font/fontello.ttf
YcChuangyeKe2019ZhongwenBiji/font/fontello.woff
YcChuangyeKe2019ZhongwenBiji/img/__init__.py
YcChuangyeKe2019ZhongwenBiji/img/annotator-glyph-sprite.png
YcChuangyeKe2019ZhongwenBiji/img/annotator-icon-sprite.png
YcChuangyeKe2019ZhongwenBiji/img/apple-touch-icon.png
YcChuangyeKe2019ZhongwenBiji/img/cancelfullscreen.png
YcChuangyeKe2019ZhongwenBiji/img/close.png
YcChuangyeKe2019ZhongwenBiji/img/fullscreen.png
YcChuangyeKe2019ZhongwenBiji/img/loader.gif
YcChuangyeKe2019ZhongwenBiji/img/menu-icon.png
YcChuangyeKe2019ZhongwenBiji/img/save.png
YcChuangyeKe2019ZhongwenBiji/img/saved.png
YcChuangyeKe2019ZhongwenBiji/img/settings-s.png
YcChuangyeKe2019ZhongwenBiji/img/settings.png
YcChuangyeKe2019ZhongwenBiji/img/star.png
YcChuangyeKe2019ZhongwenBiji/js/__init__.py
YcChuangyeKe2019ZhongwenBiji/js/epub.js
YcChuangyeKe2019ZhongwenBiji/js/epub.min.js
YcChuangyeKe2019ZhongwenBiji/js/epub.min.map
YcChuangyeKe2019ZhongwenBiji/js/hooks.min.js
YcChuangyeKe2019ZhongwenBiji/js/hooks.min.map
YcChuangyeKe2019ZhongwenBiji/js/reader.js
YcChuangyeKe2019ZhongwenBiji/js/reader.js.map
YcChuangyeKe2019ZhongwenBiji/js/reader.min.js
YcChuangyeKe2019ZhongwenBiji/js/reader.min.map
YcChuangyeKe2019ZhongwenBiji/js/hooks/__init__.py
YcChuangyeKe2019ZhongwenBiji/js/hooks/extensions/__init__.py
YcChuangyeKe2019ZhongwenBiji/js/hooks/extensions/highlight.js
yc_chuangye_ke_2019_zhongwen_biji-2024.3.5.0.dist-info/METADATA
yc_chuangye_ke_2019_zhongwen_biji-2024.3.5.0.dist-info/WHEEL
yc_chuangye_ke_2019_zhongwen_biji-2024.3.5.0.dist-info/entry_points.txt
yc_chuangye_ke_2019_zhongwen_biji-2024.3.5.0.dist-info/top_level.txt
yc_chuangye_ke_2019_zhongwen_biji-2024.3.5.0.dist-info/RECORD
